{
  "id": 1608,
  "quality": 5,
  "element": "湮灭",
  "weapon": "音感仪",
  "lv90_stats": {
    "生命": 10775,
    "攻击": 438,
    "防御": 1137,
    "暴击": "5%",
    "暴击伤害": "150%",
    "谐度破坏增幅": "0.0%"
  },
  "skills": [
    {
      "type": "常态攻击",
      "name": "生与死的乐章",
      "desc": "普攻进行最多3段的连续攻击，造成湮灭伤害。施放普攻第3段时进入重世状态。重击消耗耐力攻击目标，造成湮灭伤害。施放该技能后在一定时间内短按普攻，将会施放普攻第2段。谱曲终末弗洛洛每25秒可激活谱曲。同时满足下述3种条件时，重击替换为谱曲终末。·拥有6枚【乐声】。·谱曲处于激活状态。·不处于【定音】状态。施放谱曲终末，消耗耐力，停滞并牵引附近目标，造成湮灭伤害，本次伤害为共鸣技能伤害。每层余响可使本次伤害倍率额外增加。施放此技能时，同时视为施放声骸技能。施放此技能时，谱曲进入冷却状态，随后获得【定音】状态。空中攻击消耗耐力进行空中下落攻击，造成湮灭伤害。闪避反击成功闪避后一定时间内短按普攻，将会攻"
    },
    {
      "type": "共鸣技能",
      "name": "稍纵即逝的梦呓",
      "desc": "攻击目标，造成湮灭伤害。施放时进入重世状态。"
    },
    {
      "type": "共鸣解放",
      "name": "往日深渊的圆舞曲",
      "desc": "往日深渊的圆舞曲弗洛洛共鸣能量上限为0，往日深渊的圆舞曲不消耗共鸣能量。处于【定音】状态时，解锁往日深渊的圆舞曲。施放后退出【定音】状态，进入指挥状态，持续24秒。指挥状态攻击提升120%。弗洛洛漂浮于空中，指挥赫卡忒进行战斗，赫卡忒将继承弗洛洛的属性。赫卡忒造成的伤害不会清除目标的迷梦状态。期间按获取顺序演奏【乐声】，每枚【乐声】演奏4秒。若弗洛洛为队伍中登场角色，可施放下列指令指挥赫卡忒发动攻击，此时赫卡忒受到攻击时弗洛洛会受到伤害。·指令·普攻：点击普攻，指挥赫卡忒施放普攻·赫卡忒。弗洛洛为队伍中登场角色且赫卡忒累计施放2次普攻后，下次普攻·赫卡忒将替换为强化攻击·赫卡忒。·指令·闪避："
    },
    {
      "type": "固有技能",
      "name": "变音符",
      "desc": "施放声骸技能时，抗打断能力提升，受到伤害降低30%，持续15秒。施放致命组歌、永生组歌、声骸技能时，下一枚获得的【乐声】会变为【乐声·彩乐】。"
    },
    {
      "type": "固有技能",
      "name": "八重奏",
      "desc": "进入战斗状态获得10层余响，退出战斗状态4秒内无法触发该效果。每拥有1层余响，暴击伤害提升2.5%。余响层数达上限时，再次获得余响，每溢出1层余响，弗洛洛暴击伤害提升1%，最多通过该方式提升100%，余响层数清除时，同时清除该方式提供的暴击伤害提升效果。"
    },
    {
      "type": "变奏技能",
      "name": "致命组歌",
      "desc": "致命组歌攻击目标，造成湮灭伤害。施放该技能后在一定时间内短按普攻，将会施放普攻第3段。永生组歌进入指挥状态后，下次致命组歌替换为永生组歌，期间施放谢幕将取消本次替换。施放永生组歌，停滞目标，造成湮灭伤害，本次伤害为共鸣技能伤害。施放该技能后在一定时间内短按普攻，将会施放普攻第3段。"
    },
    {
      "type": "共鸣回路",
      "name": "新世界狂想曲",
      "desc": "普攻·亡与死的乐章处于重世状态时，地面短按普攻施放亡与死的乐章，使命中的目标停滞，随后对目标造成湮灭伤害，本次伤害为共鸣技能伤害。施放时退出重世状态。共鸣技能·永不消逝的梦呓处于重世状态时，地面短按共鸣技能施放永不消逝的梦呓，造成湮灭伤害，本次伤害为共鸣技能伤害。施放时退出重世状态。余响获取规则余响上限为24层。弗洛洛不为队伍中登场角色，施放强化攻击·弦乐·赫卡忒、强化攻击·管乐·赫卡忒、强化攻击·彩乐·赫卡忒时，可获得1层余响。弗洛洛处于非战斗状态时，每30秒会清除全部余响层数。【乐声】获取规则【乐声】上限6枚，达上限时，再次获取【乐声】，所有【乐声】将左移1格，最左侧【乐声·弦乐】、【乐声"
    },
    {
      "type": "固有技能",
      "name": "巧手烹调",
      "desc": "当前角色烹饪时有概率产出特色料理"
    },
    {
      "type": "延奏技能",
      "name": "未完成的曲目",
      "desc": "下一位登场角色湮灭伤害加深20%，重击伤害加深25%，效果持续14秒，若切换至其他角色则该效果提前结束。弗洛洛处于指挥状态时施放此技能，此次指挥状态期间，弗洛洛切换至其他角色时，赫卡忒将额外施放2次强化攻击·赫卡忒。"
    }
  ],
  "chains": [
    {
      "index": 1,
      "name": "钥匙，通往冥界的奥秘",
      "desc": "亡与死的乐章伤害倍率提升80%。永不消逝的梦呓伤害倍率提升80%。弗洛洛不处于指挥状态且不处于战斗状态4秒后，若【乐声】少于2枚，获得【乐声·彩乐】，直至【乐声】不少于2枚。"
    },
    {
      "index": 2,
      "name": "绳索，重生更新的纽带",
      "desc": "谱曲终末伤害倍率提升75%，余响对谱曲终末的倍率增加效果提升75%。施放谱曲终末时可获得14层余响。"
    },
    {
      "index": 3,
      "name": "匕首，消弭妄想的力量",
      "desc": "声骸技能伤害加深80%。施放谱曲终末期间，所有【乐声】将依次转化为【乐声·彩乐】。被强化攻击·彩乐·赫卡忒命中的目标，攻击降低20%，持续15秒。"
    },
    {
      "index": 4,
      "name": "火炬，新径启行的引导",
      "desc": "施放声骸技能时，队伍中的角色全属性伤害加成提升20%，持续30秒。"
    },
    {
      "index": 5,
      "name": "岔路，穿越生命的要地",
      "desc": "进入指挥状态时，生成领域停滞周围的目标，领域持续4秒。结束指挥状态或切换至其他角色时，将提前清除停滞效果。处于指挥状态时，受到伤害降低30%。"
    },
    {
      "index": 6,
      "name": "深夜，走出安息与终结",
      "desc": "强化攻击·赫卡忒伤害倍率提升24%。施放亡与死的乐章、永不消逝的梦呓期间，将召唤赫卡忒施放1次重世幻象·赫卡忒，造成弗洛洛攻击216.42%的湮灭伤害，命中目标时获得8层余响。本次伤害为声骸技能伤害。处于指挥状态时，若弗洛洛不为队伍中登场角色，目标受到赫卡忒和弗洛洛的伤害提升40%。处于指挥状态时，若弗洛洛为队伍中登场角色，湮灭伤害加成提升60%。"
    }
  ]
}